pycountryinfo/__init__.py
pycountryinfo/country_types.py
pycountryinfo/countryinfo.py
pycountryinfo/data/__init__.py
pycountryinfo/data/countries.json
pycountryinfo-1.0.9.dist-info/licenses/LICENSE
pycountryinfo-1.0.9.dist-info/METADATA
pycountryinfo-1.0.9.dist-info/WHEEL
pycountryinfo-1.0.9.dist-info/top_level.txt
pycountryinfo-1.0.9.dist-info/RECORD
