Metadata-Version: 2.4
Name: pycountryinfo
Version: 1.0.9
Summary: A Python package that provides information about countries, including their name, nationality, and other relevant data. Perfect for geographic data applications.
Author-email: Justice Nyame <nyamejustice2000@gmail.com>
License: MIT
Project-URL: homepage, https://github.com/Jnyame21/pycountryinfo
Classifier: Programming Language :: Python :: 3
Classifier: License :: OSI Approved :: MIT License
Classifier: Operating System :: OS Independent
Requires-Python: >=3.6
License-File: LICENSE
Requires-Dist: requests
Dynamic: license-file
